{
  "migration_multipliers": {
    "Championship": 0.77,
    "Italian Serie A": 0.871,
    "La Liga": 0.849,
    "Liga Profesional": 0.805,
    "Serie A BRA": 0.776,
    "Ekstraklasa": 0.713,
    "Prva HNL": 0.658,
    "Super Lig": 0.753,
    "Premier League": 1.0,
    "Ligue 1": 0.856,
    "Segunda Division": 0.685,
    "Primeira Liga": 0.703,
    "Liga Pro": 0.756,
    "MLS": 0.746,
    "Eliteserien": 0.74,
    "Eredivisie": 0.711,
    "Pro League": 0.752,
    "Bundesliga": 0.84,
    "Swiss Super League": 0.681,
    "Superligaen": 0.686
  },
  "fee_multipliers": {
    "Championship": 0.519,
    "Italian Serie A": 0.841,
    "La Liga": 0.779,
    "Liga Profesional": 0.345,
    "Serie A BRA": 0.412,
    "Ekstraklasa": 0.134,
    "Prva HNL": 0.231,
    "Super Lig": 0.446,
    "Premier League": 1.0,
    "Ligue 1": 0.583,
    "Segunda Division": 0.206,
    "Primeira Liga": 0.611,
    "Liga Pro": 0.257,
    "MLS": 0.322,
    "Eliteserien": 0.107,
    "Eredivisie": 0.442,
    "Pro League": 0.339,
    "Bundesliga": 0.692,
    "Swiss Super League": 0.13,
    "Superligaen": 0.281
  },
  "reference_league": "Premier League"
}